json_parser_utils/__init__.py
json_parser_utils/json_parser.py
json_parser_utils/utils.py
json_parser_utils-0.0.0.dist-info/LICENSE
json_parser_utils-0.0.0.dist-info/METADATA
json_parser_utils-0.0.0.dist-info/WHEEL
json_parser_utils-0.0.0.dist-info/top_level.txt
json_parser_utils-0.0.0.dist-info/RECORD
